Metadata-Version: 1.0
Name: slickdeals
Version: 1.0
Summary: Slickdeals command line tool
Home-page: https://github.com/MinweiShen/slickdeals
Author: Minwei Shen
Author-email: minweishen1991@gmail.com
License: UNKNOWN
Platform: UNKNOWN
